dcc_backend_common/__init__.py
dcc_backend_common/py.typed
dcc_backend_common/config/__init__.py
dcc_backend_common/config/app_config.py
dcc_backend_common/fastapi_error_handling/__init__.py
dcc_backend_common/fastapi_error_handling/error_codes.py
dcc_backend_common/fastapi_error_handling/error_exception.py
dcc_backend_common/fastapi_error_handling/error_handler.py
dcc_backend_common/fastapi_health_probes/__init__.py
dcc_backend_common/fastapi_health_probes/router.py
dcc_backend_common/logger/__init__.py
dcc_backend_common/logger/logger.py
dcc_backend_common-0.0.1.dist-info/METADATA
dcc_backend_common-0.0.1.dist-info/WHEEL
dcc_backend_common-0.0.1.dist-info/licenses/LICENSE
dcc_backend_common-0.0.1.dist-info/RECORD
