Metadata-Version: 2.4
Name: dcc-backend-common
Version: 0.0.1
Summary: Common python code used in out backend services.
Project-URL: Homepage, https://github.com/dcc-bs
Project-URL: Repository, https://github.com/DCC-BS/backend-common
Project-URL: Documentation, https://DCC-BS.github.io/documentation/
Author-email: Data Competence Center Basel-Stadt <dcc@bs.ch>, Tobias Bollinger <tobias.bollinger@bs.ch>, Yanick Schraner <yanick.schraner@bs.ch>
License-Expression: MIT
License-File: LICENSE
Keywords: python
Classifier: Intended Audience :: Developers
Classifier: Programming Language :: Python
Classifier: Programming Language :: Python :: 3
Classifier: Programming Language :: Python :: 3.10
Classifier: Programming Language :: Python :: 3.11
Classifier: Programming Language :: Python :: 3.12
Classifier: Programming Language :: Python :: 3.13
Classifier: Topic :: Software Development :: Libraries :: Python Modules
Requires-Python: <4.0,>=3.12
Requires-Dist: datasets>=4.4.1
Requires-Dist: dspy>=3.0.4
Requires-Dist: jiwer>=4.0.0
Requires-Dist: pydantic>=2.12.5
Requires-Dist: python-dotenv>=1.0.1
Requires-Dist: structlog>=25.1.0
Provides-Extra: fastapi
Requires-Dist: aiohttp>=3.13.2; extra == 'fastapi'
Requires-Dist: fastapi<1.0,>=0.115; extra == 'fastapi'
